setup.cfg
setup.py
bpipe/__init__.py
bpipe/pipe.py
bpipe/sources.py
bpipe/utils.py
bpipe.egg-info/PKG-INFO
bpipe.egg-info/SOURCES.txt
bpipe.egg-info/dependency_links.txt
bpipe.egg-info/entry_points.txt
bpipe.egg-info/top_level.txt
examples/__init__.py
examples/first.py
examples/hello.py
examples/peek.py
examples/wordcount.py