Metadata-Version: 1.1
Name: bpipe
Version: 1.0.0
Summary: Minimal & Simple Pipeline for Python
Home-page: https://github.com/jepemo/basic-pipeline
Author: Jeremies Pérez Morata
Author-email: jeremiespm@gmail.com
License: GPL-v3
Keywords: pipeline,development,streaming,data processing,utils
Platform: UNKNOWN
Classifier: Development Status :: 5 - Production/Stable
Classifier: Intended Audience :: Developers
Classifier: Topic :: Software Development :: Libraries :: Python Modules
Classifier: License :: OSI Approved :: GNU General Public License v3 (GPLv3)
Classifier: Programming Language :: Python :: 3
Classifier: Programming Language :: Python :: 3.3
Classifier: Programming Language :: Python :: 3.4
Classifier: Programming Language :: Python :: 3.5
Classifier: Programming Language :: Python :: 3.6
